redbacktechpy/__init__.py
redbacktechpy/constants.py
redbacktechpy/exceptions.py
redbacktechpy/model.py
redbacktechpy/redbacktech_client.py
redbacktechpy/str_enum.py
redbacktechpy-2026.1.2.dist-info/licenses/LICENSE
redbacktechpy-2026.1.2.dist-info/METADATA
redbacktechpy-2026.1.2.dist-info/WHEEL
redbacktechpy-2026.1.2.dist-info/top_level.txt
redbacktechpy-2026.1.2.dist-info/RECORD
