Metadata-Version: 2.4
Name: redbacktechpy
Version: 2026.1.2
Summary: Python Module to support Home Assistant integration with Redback Technologies Smart Hybrid Inverter
Author-email: Chris Abberley <unlisted@gmail.com>
Project-URL: Homepage, https://github.com/cabberley/redbacktechpy
Project-URL: Issues, https://github.com/cabberley/redbacktechpy/issues
Classifier: Programming Language :: Python :: 3
Classifier: Operating System :: OS Independent
Requires-Python: >=3.10
License-File: LICENSE
Requires-Dist: aiohttp>=3.8.1
Requires-Dist: tzlocal>=4.2
Requires-Dist: bs4>=0.0.1
Requires-Dist: beautifulsoup4>=4.10.0
Dynamic: license-file
